{"result": [
 {
  "run": 355135, 
  "write_miniaod": false, 
  "scram_arch": "slc7_amd64_gcc10", 
  "write_aod": false, 
  "write_reco": false, 
  "alca_skim": "AlCaPCCZeroBias,RawPCCProducer", 
  "cmssw": "CMSSW_12_3_6", 
  "physics_skim": null, 
  "write_dqm": false, 
  "scenario": "AlCaLumiPixels_Run3", 
  "global_tag": "123X_dataRun3_Prompt_v12", 
  "multicore": 8, 
  "dqm_seq": null, 
  "primary_dataset": "AlCaLumiPixelsCountsPrompt"
},{
  "run": 355135, 
  "write_miniaod": true, 
  "scram_arch": "slc7_amd64_gcc10", 
  "write_aod": true, 
  "write_reco": false, 
  "alca_skim": "EcalCalPi0Calib,EcalCalEtaCalib", 
  "cmssw": "CMSSW_12_3_6", 
  "physics_skim": null, 
  "write_dqm": false, 
  "scenario": "ppEra_Run3", 
  "global_tag": "123X_dataRun3_Prompt_v12", 
  "multicore": 8, 
  "dqm_seq": null, 
  "primary_dataset": "AlCaP0"
},{
  "run": 355135, 
  "write_miniaod": true, 
  "scram_arch": "slc7_amd64_gcc10", 
  "write_aod": true, 
  "write_reco": false, 
  "alca_skim": "EcalCalPhiSym", 
  "cmssw": "CMSSW_12_3_6", 
  "physics_skim": null, 
  "write_dqm": false, 
  "scenario": "ppEra_Run3", 
  "global_tag": "123X_dataRun3_Prompt_v12", 
  "multicore": 8, 
  "dqm_seq": null, 
  "primary_dataset": "AlCaPhiSym"
},{
  "run": 355135, 
  "write_miniaod": true, 
  "scram_arch": "slc7_amd64_gcc10", 
  "write_aod": true, 
  "write_reco": false, 
  "alca_skim": null, 
  "cmssw": "CMSSW_12_3_6", 
  "physics_skim": "LogError,LogErrorMonitor", 
  "write_dqm": true, 
  "scenario": "ppEra_Run3", 
  "global_tag": "123X_dataRun3_Prompt_v12", 
  "multicore": 8, 
  "dqm_seq": "@common", 
  "primary_dataset": "BTagMu"
},{
  "run": 355135, 
  "write_miniaod": true, 
  "scram_arch": "slc7_amd64_gcc10", 
  "write_aod": true, 
  "write_reco": false, 
  "alca_skim": "TkAlMinBias,SiStripCalMinBias,HcalCalIsoTrk,HcalCalIsolatedBunchSelector", 
  "cmssw": "CMSSW_12_3_6", 
  "physics_skim": "EcalActivity,LogError,LogErrorMonitor", 
  "write_dqm": true, 
  "scenario": "ppEra_Run3", 
  "global_tag": "123X_dataRun3_Prompt_v12", 
  "multicore": 8, 
  "dqm_seq": "@common,@L1TMon,@hcal", 
  "primary_dataset": "Commissioning"
},{
  "run": 355135, 
  "write_miniaod": false, 
  "scram_arch": "slc7_amd64_gcc10", 
  "write_aod": true, 
  "write_reco": false, 
  "alca_skim": "SiStripCalCosmics,SiPixelCalCosmics,TkAlCosmics0T,MuAlGlobalCosmics,SiStripCalCosmicsNano", 
  "cmssw": "CMSSW_12_3_6", 
  "physics_skim": "CosmicSP,CosmicTP,LogError,LogErrorMonitor", 
  "write_dqm": true, 
  "scenario": "cosmicsEra_Run3", 
  "global_tag": "123X_dataRun3_Prompt_v12", 
  "multicore": 8, 
  "dqm_seq": null, 
  "primary_dataset": "Cosmics"
},{
  "run": 355135, 
  "write_miniaod": true, 
  "scram_arch": "slc7_amd64_gcc10", 
  "write_aod": true, 
  "write_reco": false, 
  "alca_skim": null, 
  "cmssw": "CMSSW_12_3_6", 
  "physics_skim": "EXODisplacedJet,LogError,LogErrorMonitor", 
  "write_dqm": true, 
  "scenario": "ppEra_Run3", 
  "global_tag": "123X_dataRun3_Prompt_v12", 
  "multicore": 8, 
  "dqm_seq": "@common", 
  "primary_dataset": "DisplacedJet"
},{
  "run": 355135, 
  "write_miniaod": true, 
  "scram_arch": "slc7_amd64_gcc10", 
  "write_aod": true, 
  "write_reco": false, 
  "alca_skim": "TkAlZMuMu,MuAlCalIsolatedMu,TkAlDiMuonAndVertex", 
  "cmssw": "CMSSW_12_3_6", 
  "physics_skim": "LogError,LogErrorMonitor", 
  "write_dqm": true, 
  "scenario": "ppEra_Run3", 
  "global_tag": "123X_dataRun3_Prompt_v12", 
  "multicore": 8, 
  "dqm_seq": "@common,@muon,@lumi,@L1TMuon", 
  "primary_dataset": "DoubleMuon"
},{
  "run": 355135, 
  "write_miniaod": true, 
  "scram_arch": "slc7_amd64_gcc10", 
  "write_aod": true, 
  "write_reco": false, 
  "alca_skim": "TkAlJpsiMuMu,TkAlUpsilonMuMu", 
  "cmssw": "CMSSW_12_3_6", 
  "physics_skim": "LogError,LogErrorMonitor,BPHSkim,MuonPOGJPsiSkim", 
  "write_dqm": true, 
  "scenario": "ppEra_Run3", 
  "global_tag": "123X_dataRun3_Prompt_v12", 
  "multicore": 8, 
  "dqm_seq": "@common,@muon", 
  "primary_dataset": "DoubleMuonLowMass"
},{
  "run": 355135, 
  "write_miniaod": true, 
  "scram_arch": "slc7_amd64_gcc10", 
  "write_aod": true, 
  "write_reco": false, 
  "alca_skim": "EcalUncalZElectron,EcalUncalWElectron,HcalCalIterativePhiSym,HcalCalIsoTrkProducerFilter,EcalESAlign", 
  "cmssw": "CMSSW_12_3_6", 
  "physics_skim": "EXOMONOPOLE,ZElectron,LogError,LogErrorMonitor", 
  "write_dqm": true, 
  "scenario": "ppEra_Run3", 
  "global_tag": "123X_dataRun3_Prompt_v12", 
  "multicore": 8, 
  "dqm_seq": "@common,@ecal,@egamma,@L1TEgamma", 
  "primary_dataset": "EGamma"
},{
  "run": 355135, 
  "write_miniaod": true, 
  "scram_arch": "slc7_amd64_gcc10", 
  "write_aod": true, 
  "write_reco": false, 
  "alca_skim": null, 
  "cmssw": "CMSSW_12_3_6", 
  "physics_skim": null, 
  "write_dqm": true, 
  "scenario": "ppEra_Run3", 
  "global_tag": "123X_dataRun3_Prompt_v12", 
  "multicore": 8, 
  "dqm_seq": "@common", 
  "primary_dataset": "EmptyBX"
},{
  "run": 355135, 
  "write_miniaod": true, 
  "scram_arch": "slc7_amd64_gcc10", 
  "write_aod": true, 
  "write_reco": false, 
  "alca_skim": null, 
  "cmssw": "CMSSW_12_3_6", 
  "physics_skim": null, 
  "write_dqm": true, 
  "scenario": "ppEra_Run3", 
  "global_tag": "123X_dataRun3_Prompt_v12", 
  "multicore": 8, 
  "dqm_seq": "@common", 
  "primary_dataset": "HINCaloJets"
},{
  "run": 355135, 
  "write_miniaod": true, 
  "scram_arch": "slc7_amd64_gcc10", 
  "write_aod": true, 
  "write_reco": false, 
  "alca_skim": null, 
  "cmssw": "CMSSW_12_3_6", 
  "physics_skim": null, 
  "write_dqm": true, 
  "scenario": "ppEra_Run3", 
  "global_tag": "123X_dataRun3_Prompt_v12", 
  "multicore": 8, 
  "dqm_seq": "@common", 
  "primary_dataset": "HINPFJets"
},{
  "run": 355135, 
  "write_miniaod": true, 
  "scram_arch": "slc7_amd64_gcc10", 
  "write_aod": true, 
  "write_reco": false, 
  "alca_skim": "TkAlMinBias", 
  "cmssw": "CMSSW_12_3_6", 
  "physics_skim": "LogError,LogErrorMonitor", 
  "write_dqm": true, 
  "scenario": "ppEra_Run3", 
  "global_tag": "123X_dataRun3_Prompt_v12", 
  "multicore": 8, 
  "dqm_seq": "@common,@ecal,@jetmet,@L1TMon,@hcal,@L1TEgamma", 
  "primary_dataset": "HLTPhysics"
},{
  "run": 355135, 
  "write_miniaod": true, 
  "scram_arch": "slc7_amd64_gcc10", 
  "write_aod": true, 
  "write_reco": false, 
  "alca_skim": "HcalCalMinBias", 
  "cmssw": "CMSSW_12_3_6", 
  "physics_skim": "LogError,LogErrorMonitor", 
  "write_dqm": true, 
  "scenario": "hcalnzsEra_Run3", 
  "global_tag": "123X_dataRun3_Prompt_v12", 
  "multicore": 8, 
  "dqm_seq": "@common,@L1TMon,@hcal", 
  "primary_dataset": "HcalNZS"
},{
  "run": 355135, 
  "write_miniaod": true, 
  "scram_arch": "slc7_amd64_gcc10", 
  "write_aod": true, 
  "write_reco": false, 
  "alca_skim": null, 
  "cmssw": "CMSSW_12_3_6", 
  "physics_skim": null, 
  "write_dqm": true, 
  "scenario": "ppEra_Run3", 
  "global_tag": "123X_dataRun3_Prompt_v12", 
  "multicore": 8, 
  "dqm_seq": "@common", 
  "primary_dataset": "HighPtLowerPhotons"
},{
  "run": 355135, 
  "write_miniaod": true, 
  "scram_arch": "slc7_amd64_gcc10", 
  "write_aod": true, 
  "write_reco": false, 
  "alca_skim": null, 
  "cmssw": "CMSSW_12_3_6", 
  "physics_skim": null, 
  "write_dqm": true, 
  "scenario": "ppEra_Run3", 
  "global_tag": "123X_dataRun3_Prompt_v12", 
  "multicore": 8, 
  "dqm_seq": "@common", 
  "primary_dataset": "HighPtPhoton30AndZ"
},{
  "run": 355135, 
  "write_miniaod": true, 
  "scram_arch": "slc7_amd64_gcc10", 
  "write_aod": true, 
  "write_reco": false, 
  "alca_skim": null, 
  "cmssw": "CMSSW_12_3_6", 
  "physics_skim": null, 
  "write_dqm": false, 
  "scenario": "ppEra_Run3", 
  "global_tag": "123X_dataRun3_Prompt_v12", 
  "multicore": 8, 
  "dqm_seq": null, 
  "primary_dataset": "IsolatedBunch"
},{
  "run": 355135, 
  "write_miniaod": true, 
  "scram_arch": "slc7_amd64_gcc10", 
  "write_aod": true, 
  "write_reco": false, 
  "alca_skim": "HcalCalIsoTrkProducerFilter,TkAlJetHT", 
  "cmssw": "CMSSW_12_3_6", 
  "physics_skim": "JetHTJetPlusHOFilter,LogError,LogErrorMonitor", 
  "write_dqm": true, 
  "scenario": "ppEra_Run3", 
  "global_tag": "123X_dataRun3_Prompt_v12", 
  "multicore": 8, 
  "dqm_seq": "@common,@jetmet,@L1TMon,@hcal", 
  "primary_dataset": "JetHT"
},{
  "run": 355135, 
  "write_miniaod": true, 
  "scram_arch": "slc7_amd64_gcc10", 
  "write_aod": true, 
  "write_reco": false, 
  "alca_skim": null, 
  "cmssw": "CMSSW_12_3_6", 
  "physics_skim": null, 
  "write_dqm": false, 
  "scenario": "ppEra_Run3", 
  "global_tag": "123X_dataRun3_Prompt_v12", 
  "multicore": 8, 
  "dqm_seq": "@common", 
  "primary_dataset": "L1Accept"
},{
  "run": 355135, 
  "write_miniaod": true, 
  "scram_arch": "slc7_amd64_gcc10", 
  "write_aod": true, 
  "write_reco": false, 
  "alca_skim": "HcalCalNoise", 
  "cmssw": "CMSSW_12_3_6", 
  "physics_skim": "EXOMONOPOLE,HighMET,LogError,LogErrorMonitor", 
  "write_dqm": true, 
  "scenario": "ppEra_Run3", 
  "global_tag": "123X_dataRun3_Prompt_v12", 
  "multicore": 8, 
  "dqm_seq": "@common,@jetmet,@L1TMon,@hcal", 
  "primary_dataset": "MET"
},{
  "run": 355135, 
  "write_miniaod": true, 
  "scram_arch": "slc7_amd64_gcc10", 
  "write_aod": true, 
  "write_reco": false, 
  "alca_skim": "SiStripCalZeroBias,SiStripCalMinBias,TkAlMinBias,HcalCalHO,HcalCalIterativePhiSym,HcalCalHBHEMuonProducerFilter,HcalCalIsoTrkProducerFilter", 
  "cmssw": "CMSSW_12_3_6", 
  "physics_skim": null, 
  "write_dqm": true, 
  "scenario": "ppEra_Run3", 
  "global_tag": "123X_dataRun3_Prompt_v12", 
  "multicore": 8, 
  "dqm_seq": "@commonSiStripZeroBias,@ecal,@L1TMon,@hcal,@muon,@jetmet", 
  "primary_dataset": "MinimumBias"
},{
  "run": 355135, 
  "write_miniaod": true, 
  "scram_arch": "slc7_amd64_gcc10", 
  "write_aod": true, 
  "write_reco": false, 
  "alca_skim": null, 
  "cmssw": "CMSSW_12_3_6", 
  "physics_skim": "TopMuEG,LogError,LogErrorMonitor", 
  "write_dqm": true, 
  "scenario": "ppEra_Run3", 
  "global_tag": "123X_dataRun3_Prompt_v12", 
  "multicore": 8, 
  "dqm_seq": "@common", 
  "primary_dataset": "MuonEG"
},{
  "run": 355135, 
  "write_miniaod": true, 
  "scram_arch": "slc7_amd64_gcc10", 
  "write_aod": true, 
  "write_reco": false, 
  "alca_skim": "TkAlCosmicsInCollisions", 
  "cmssw": "CMSSW_12_3_6", 
  "physics_skim": "EXONoBPTXSkim,LogError,LogErrorMonitor", 
  "write_dqm": true, 
  "scenario": "ppEra_Run3", 
  "global_tag": "123X_dataRun3_Prompt_v12", 
  "multicore": 8, 
  "dqm_seq": "@common", 
  "primary_dataset": "NoBPTX"
},{
  "run": 355135, 
  "write_miniaod": true, 
  "scram_arch": "slc7_amd64_gcc10", 
  "write_aod": true, 
  "write_reco": false, 
  "alca_skim": null, 
  "cmssw": "CMSSW_12_3_6", 
  "physics_skim": null, 
  "write_dqm": false, 
  "scenario": "ppEra_Run3", 
  "global_tag": "123X_dataRun3_Prompt_v12", 
  "multicore": 8, 
  "dqm_seq": null, 
  "primary_dataset": "RPCMonitor"
},{
  "run": 355135, 
  "write_miniaod": true, 
  "scram_arch": "slc7_amd64_gcc10", 
  "write_aod": true, 
  "write_reco": false, 
  "alca_skim": "TkAlMuonIsolated,HcalCalIterativePhiSym,MuAlCalIsolatedMu,HcalCalHO,HcalCalHBHEMuonProducerFilter,SiPixelCalSingleMuonLoose,SiPixelCalSingleMuonTight", 
  "cmssw": "CMSSW_12_3_6", 
  "physics_skim": "MuonPOGSkim,MuTau,ZMu,LogError,LogErrorMonitor", 
  "write_dqm": true, 
  "scenario": "ppEra_Run3", 
  "global_tag": "123X_dataRun3_Prompt_v12", 
  "multicore": 8, 
  "dqm_seq": "@common,@muon,@lumi,@L1TMuon", 
  "primary_dataset": "SingleMuon"
},{
  "run": 355135, 
  "write_miniaod": true, 
  "scram_arch": "slc7_amd64_gcc10", 
  "write_aod": true, 
  "write_reco": false, 
  "alca_skim": null, 
  "cmssw": "CMSSW_12_3_6", 
  "physics_skim": "LogError,LogErrorMonitor", 
  "write_dqm": true, 
  "scenario": "ppEra_Run3", 
  "global_tag": "123X_dataRun3_Prompt_v12", 
  "multicore": 8, 
  "dqm_seq": "@common", 
  "primary_dataset": "Tau"
},{
  "run": 355135, 
  "write_miniaod": true, 
  "scram_arch": "slc7_amd64_gcc10", 
  "write_aod": true, 
  "write_reco": false, 
  "alca_skim": "SiStripCalZeroBias,TkAlMinBias,SiStripCalMinBias", 
  "cmssw": "CMSSW_12_3_6", 
  "physics_skim": "LogError,LogErrorMonitor", 
  "write_dqm": true, 
  "scenario": "ppEra_Run3", 
  "global_tag": "123X_dataRun3_Prompt_v12", 
  "multicore": 8, 
  "dqm_seq": "@commonSiStripZeroBias,@ecal,@L1TMon,@hcal,@muon,@jetmet,@ctpps", 
  "primary_dataset": "ZeroBias"
},{
  "run": 355135, 
  "write_miniaod": true, 
  "scram_arch": "slc7_amd64_gcc10", 
  "write_aod": true, 
  "write_reco": false, 
  "alca_skim": "SiStripCalZeroBias,TkAlMinBias,SiStripCalMinBias", 
  "cmssw": "CMSSW_12_3_6", 
  "physics_skim": "LogError,LogErrorMonitor", 
  "write_dqm": true, 
  "scenario": "ppEra_Run3", 
  "global_tag": "123X_dataRun3_Prompt_v12", 
  "multicore": 8, 
  "dqm_seq": "@commonSiStripZeroBias,@ecal,@L1TMon,@hcal,@muon,@jetmet,@ctpps", 
  "primary_dataset": "ZeroBias0"
},{
  "run": 355135, 
  "write_miniaod": true, 
  "scram_arch": "slc7_amd64_gcc10", 
  "write_aod": true, 
  "write_reco": false, 
  "alca_skim": "SiStripCalZeroBias,TkAlMinBias,SiStripCalMinBias", 
  "cmssw": "CMSSW_12_3_6", 
  "physics_skim": "LogError,LogErrorMonitor", 
  "write_dqm": true, 
  "scenario": "ppEra_Run3", 
  "global_tag": "123X_dataRun3_Prompt_v12", 
  "multicore": 8, 
  "dqm_seq": "@commonSiStripZeroBias,@ecal,@L1TMon,@hcal,@muon,@jetmet,@ctpps", 
  "primary_dataset": "ZeroBias1"
},{
  "run": 355135, 
  "write_miniaod": true, 
  "scram_arch": "slc7_amd64_gcc10", 
  "write_aod": true, 
  "write_reco": false, 
  "alca_skim": "SiStripCalZeroBias,TkAlMinBias,SiStripCalMinBias", 
  "cmssw": "CMSSW_12_3_6", 
  "physics_skim": "LogError,LogErrorMonitor", 
  "write_dqm": true, 
  "scenario": "ppEra_Run3", 
  "global_tag": "123X_dataRun3_Prompt_v12", 
  "multicore": 8, 
  "dqm_seq": "@commonSiStripZeroBias,@ecal,@L1TMon,@hcal,@muon,@jetmet,@ctpps", 
  "primary_dataset": "ZeroBias10"
},{
  "run": 355135, 
  "write_miniaod": true, 
  "scram_arch": "slc7_amd64_gcc10", 
  "write_aod": true, 
  "write_reco": false, 
  "alca_skim": "SiStripCalZeroBias,TkAlMinBias,SiStripCalMinBias", 
  "cmssw": "CMSSW_12_3_6", 
  "physics_skim": "LogError,LogErrorMonitor", 
  "write_dqm": true, 
  "scenario": "ppEra_Run3", 
  "global_tag": "123X_dataRun3_Prompt_v12", 
  "multicore": 8, 
  "dqm_seq": "@commonSiStripZeroBias,@ecal,@L1TMon,@hcal,@muon,@jetmet,@ctpps", 
  "primary_dataset": "ZeroBias11"
},{
  "run": 355135, 
  "write_miniaod": true, 
  "scram_arch": "slc7_amd64_gcc10", 
  "write_aod": true, 
  "write_reco": false, 
  "alca_skim": "SiStripCalZeroBias,TkAlMinBias,SiStripCalMinBias", 
  "cmssw": "CMSSW_12_3_6", 
  "physics_skim": "LogError,LogErrorMonitor", 
  "write_dqm": true, 
  "scenario": "ppEra_Run3", 
  "global_tag": "123X_dataRun3_Prompt_v12", 
  "multicore": 8, 
  "dqm_seq": "@commonSiStripZeroBias,@ecal,@L1TMon,@hcal,@muon,@jetmet,@ctpps", 
  "primary_dataset": "ZeroBias12"
},{
  "run": 355135, 
  "write_miniaod": true, 
  "scram_arch": "slc7_amd64_gcc10", 
  "write_aod": true, 
  "write_reco": false, 
  "alca_skim": "SiStripCalZeroBias,TkAlMinBias,SiStripCalMinBias", 
  "cmssw": "CMSSW_12_3_6", 
  "physics_skim": "LogError,LogErrorMonitor", 
  "write_dqm": true, 
  "scenario": "ppEra_Run3", 
  "global_tag": "123X_dataRun3_Prompt_v12", 
  "multicore": 8, 
  "dqm_seq": "@commonSiStripZeroBias,@ecal,@L1TMon,@hcal,@muon,@jetmet,@ctpps", 
  "primary_dataset": "ZeroBias13"
},{
  "run": 355135, 
  "write_miniaod": true, 
  "scram_arch": "slc7_amd64_gcc10", 
  "write_aod": true, 
  "write_reco": false, 
  "alca_skim": "SiStripCalZeroBias,TkAlMinBias,SiStripCalMinBias", 
  "cmssw": "CMSSW_12_3_6", 
  "physics_skim": "LogError,LogErrorMonitor", 
  "write_dqm": true, 
  "scenario": "ppEra_Run3", 
  "global_tag": "123X_dataRun3_Prompt_v12", 
  "multicore": 8, 
  "dqm_seq": "@commonSiStripZeroBias,@ecal,@L1TMon,@hcal,@muon,@jetmet,@ctpps", 
  "primary_dataset": "ZeroBias14"
},{
  "run": 355135, 
  "write_miniaod": true, 
  "scram_arch": "slc7_amd64_gcc10", 
  "write_aod": true, 
  "write_reco": false, 
  "alca_skim": "SiStripCalZeroBias,TkAlMinBias,SiStripCalMinBias", 
  "cmssw": "CMSSW_12_3_6", 
  "physics_skim": "LogError,LogErrorMonitor", 
  "write_dqm": true, 
  "scenario": "ppEra_Run3", 
  "global_tag": "123X_dataRun3_Prompt_v12", 
  "multicore": 8, 
  "dqm_seq": "@commonSiStripZeroBias,@ecal,@L1TMon,@hcal,@muon,@jetmet,@ctpps", 
  "primary_dataset": "ZeroBias15"
},{
  "run": 355135, 
  "write_miniaod": true, 
  "scram_arch": "slc7_amd64_gcc10", 
  "write_aod": true, 
  "write_reco": false, 
  "alca_skim": "SiStripCalZeroBias,TkAlMinBias,SiStripCalMinBias", 
  "cmssw": "CMSSW_12_3_6", 
  "physics_skim": "LogError,LogErrorMonitor", 
  "write_dqm": true, 
  "scenario": "ppEra_Run3", 
  "global_tag": "123X_dataRun3_Prompt_v12", 
  "multicore": 8, 
  "dqm_seq": "@commonSiStripZeroBias,@ecal,@L1TMon,@hcal,@muon,@jetmet,@ctpps", 
  "primary_dataset": "ZeroBias16"
},{
  "run": 355135, 
  "write_miniaod": true, 
  "scram_arch": "slc7_amd64_gcc10", 
  "write_aod": true, 
  "write_reco": false, 
  "alca_skim": "SiStripCalZeroBias,TkAlMinBias,SiStripCalMinBias", 
  "cmssw": "CMSSW_12_3_6", 
  "physics_skim": "LogError,LogErrorMonitor", 
  "write_dqm": true, 
  "scenario": "ppEra_Run3", 
  "global_tag": "123X_dataRun3_Prompt_v12", 
  "multicore": 8, 
  "dqm_seq": "@commonSiStripZeroBias,@ecal,@L1TMon,@hcal,@muon,@jetmet,@ctpps", 
  "primary_dataset": "ZeroBias17"
},{
  "run": 355135, 
  "write_miniaod": true, 
  "scram_arch": "slc7_amd64_gcc10", 
  "write_aod": true, 
  "write_reco": false, 
  "alca_skim": "SiStripCalZeroBias,TkAlMinBias,SiStripCalMinBias", 
  "cmssw": "CMSSW_12_3_6", 
  "physics_skim": "LogError,LogErrorMonitor", 
  "write_dqm": true, 
  "scenario": "ppEra_Run3", 
  "global_tag": "123X_dataRun3_Prompt_v12", 
  "multicore": 8, 
  "dqm_seq": "@commonSiStripZeroBias,@ecal,@L1TMon,@hcal,@muon,@jetmet,@ctpps", 
  "primary_dataset": "ZeroBias18"
},{
  "run": 355135, 
  "write_miniaod": true, 
  "scram_arch": "slc7_amd64_gcc10", 
  "write_aod": true, 
  "write_reco": false, 
  "alca_skim": "SiStripCalZeroBias,TkAlMinBias,SiStripCalMinBias", 
  "cmssw": "CMSSW_12_3_6", 
  "physics_skim": "LogError,LogErrorMonitor", 
  "write_dqm": true, 
  "scenario": "ppEra_Run3", 
  "global_tag": "123X_dataRun3_Prompt_v12", 
  "multicore": 8, 
  "dqm_seq": "@commonSiStripZeroBias,@ecal,@L1TMon,@hcal,@muon,@jetmet,@ctpps", 
  "primary_dataset": "ZeroBias19"
},{
  "run": 355135, 
  "write_miniaod": true, 
  "scram_arch": "slc7_amd64_gcc10", 
  "write_aod": true, 
  "write_reco": false, 
  "alca_skim": "SiStripCalZeroBias,TkAlMinBias,SiStripCalMinBias", 
  "cmssw": "CMSSW_12_3_6", 
  "physics_skim": "LogError,LogErrorMonitor", 
  "write_dqm": true, 
  "scenario": "ppEra_Run3", 
  "global_tag": "123X_dataRun3_Prompt_v12", 
  "multicore": 8, 
  "dqm_seq": "@commonSiStripZeroBias,@ecal,@L1TMon,@hcal,@muon,@jetmet,@ctpps", 
  "primary_dataset": "ZeroBias2"
},{
  "run": 355135, 
  "write_miniaod": true, 
  "scram_arch": "slc7_amd64_gcc10", 
  "write_aod": true, 
  "write_reco": false, 
  "alca_skim": "SiStripCalZeroBias,TkAlMinBias,SiStripCalMinBias", 
  "cmssw": "CMSSW_12_3_6", 
  "physics_skim": "LogError,LogErrorMonitor", 
  "write_dqm": true, 
  "scenario": "ppEra_Run3", 
  "global_tag": "123X_dataRun3_Prompt_v12", 
  "multicore": 8, 
  "dqm_seq": "@commonSiStripZeroBias,@ecal,@L1TMon,@hcal,@muon,@jetmet,@ctpps", 
  "primary_dataset": "ZeroBias3"
},{
  "run": 355135, 
  "write_miniaod": true, 
  "scram_arch": "slc7_amd64_gcc10", 
  "write_aod": true, 
  "write_reco": false, 
  "alca_skim": "SiStripCalZeroBias,TkAlMinBias,SiStripCalMinBias", 
  "cmssw": "CMSSW_12_3_6", 
  "physics_skim": "LogError,LogErrorMonitor", 
  "write_dqm": true, 
  "scenario": "ppEra_Run3", 
  "global_tag": "123X_dataRun3_Prompt_v12", 
  "multicore": 8, 
  "dqm_seq": "@commonSiStripZeroBias,@ecal,@L1TMon,@hcal,@muon,@jetmet,@ctpps", 
  "primary_dataset": "ZeroBias4"
},{
  "run": 355135, 
  "write_miniaod": true, 
  "scram_arch": "slc7_amd64_gcc10", 
  "write_aod": true, 
  "write_reco": false, 
  "alca_skim": "SiStripCalZeroBias,TkAlMinBias,SiStripCalMinBias", 
  "cmssw": "CMSSW_12_3_6", 
  "physics_skim": "LogError,LogErrorMonitor", 
  "write_dqm": true, 
  "scenario": "ppEra_Run3", 
  "global_tag": "123X_dataRun3_Prompt_v12", 
  "multicore": 8, 
  "dqm_seq": "@commonSiStripZeroBias,@ecal,@L1TMon,@hcal,@muon,@jetmet,@ctpps", 
  "primary_dataset": "ZeroBias5"
},{
  "run": 355135, 
  "write_miniaod": true, 
  "scram_arch": "slc7_amd64_gcc10", 
  "write_aod": true, 
  "write_reco": false, 
  "alca_skim": "SiStripCalZeroBias,TkAlMinBias,SiStripCalMinBias", 
  "cmssw": "CMSSW_12_3_6", 
  "physics_skim": "LogError,LogErrorMonitor", 
  "write_dqm": true, 
  "scenario": "ppEra_Run3", 
  "global_tag": "123X_dataRun3_Prompt_v12", 
  "multicore": 8, 
  "dqm_seq": "@commonSiStripZeroBias,@ecal,@L1TMon,@hcal,@muon,@jetmet,@ctpps", 
  "primary_dataset": "ZeroBias6"
},{
  "run": 355135, 
  "write_miniaod": true, 
  "scram_arch": "slc7_amd64_gcc10", 
  "write_aod": true, 
  "write_reco": false, 
  "alca_skim": "SiStripCalZeroBias,TkAlMinBias,SiStripCalMinBias", 
  "cmssw": "CMSSW_12_3_6", 
  "physics_skim": "LogError,LogErrorMonitor", 
  "write_dqm": true, 
  "scenario": "ppEra_Run3", 
  "global_tag": "123X_dataRun3_Prompt_v12", 
  "multicore": 8, 
  "dqm_seq": "@commonSiStripZeroBias,@ecal,@L1TMon,@hcal,@muon,@jetmet,@ctpps", 
  "primary_dataset": "ZeroBias7"
},{
  "run": 355135, 
  "write_miniaod": true, 
  "scram_arch": "slc7_amd64_gcc10", 
  "write_aod": true, 
  "write_reco": false, 
  "alca_skim": "SiStripCalZeroBias,TkAlMinBias,SiStripCalMinBias", 
  "cmssw": "CMSSW_12_3_6", 
  "physics_skim": "LogError,LogErrorMonitor", 
  "write_dqm": true, 
  "scenario": "ppEra_Run3", 
  "global_tag": "123X_dataRun3_Prompt_v12", 
  "multicore": 8, 
  "dqm_seq": "@commonSiStripZeroBias,@ecal,@L1TMon,@hcal,@muon,@jetmet,@ctpps", 
  "primary_dataset": "ZeroBias8"
},{
  "run": 355135, 
  "write_miniaod": true, 
  "scram_arch": "slc7_amd64_gcc10", 
  "write_aod": true, 
  "write_reco": false, 
  "alca_skim": "SiStripCalZeroBias,TkAlMinBias,SiStripCalMinBias", 
  "cmssw": "CMSSW_12_3_6", 
  "physics_skim": "LogError,LogErrorMonitor", 
  "write_dqm": true, 
  "scenario": "ppEra_Run3", 
  "global_tag": "123X_dataRun3_Prompt_v12", 
  "multicore": 8, 
  "dqm_seq": "@commonSiStripZeroBias,@ecal,@L1TMon,@hcal,@muon,@jetmet,@ctpps", 
  "primary_dataset": "ZeroBias9"
}]}
